pspkg.py
pspkg-0.1.1.dist-info/METADATA
pspkg-0.1.1.dist-info/WHEEL
pspkg-0.1.1.dist-info/entry_points.txt
pspkg-0.1.1.dist-info/licenses/LICENSE.md
pspkg-0.1.1.dist-info/RECORD
