Metadata-Version: 2.4
Name: pspkg
Version: 0.1.1
Summary: Check for package compatibility with PyScript.
Project-URL: Homepage, https://github.com/pyscript/pspkg
Project-URL: Repository, https://github.com/pyscript/pspkg.git
Author-email: "Nicholas H.Tollervey" <ntoll@ntoll.org>
Maintainer-email: "Nicholas H.Tollervey" <ntoll@ntoll.org>
License-Expression: MIT
License-File: LICENSE.md
Keywords: api,packages,pyscript
Classifier: Development Status :: 3 - Alpha
Classifier: Environment :: Console
Classifier: Environment :: WebAssembly :: Emscripten
Classifier: Intended Audience :: Developers
Classifier: License :: OSI Approved :: MIT License
Classifier: Topic :: Utilities
Requires-Python: >=3.10
Requires-Dist: requests
Provides-Extra: dev
Requires-Dist: black; extra == 'dev'
Requires-Dist: build; extra == 'dev'
Requires-Dist: hatch; extra == 'dev'
Requires-Dist: twine; extra == 'dev'
